active_pr/__init__.py
active_pr/active.py
active_pr/api.py
active_pr/cli.py
active_pr/exception.py
active_pr/version.py
active_pr-0.1.0.dist-info/LICENSE
active_pr-0.1.0.dist-info/METADATA
active_pr-0.1.0.dist-info/WHEEL
active_pr-0.1.0.dist-info/entry_points.txt
active_pr-0.1.0.dist-info/RECORD
