Metadata-Version: 2.1
Name: active-pr
Version: 0.1.0
Summary: an active report of PRs in the github
Home-page: https://github.com/kyoto7250/active_pr
License: MIT
Keywords: api,github,cli,report
Author: kyoto7250
Author-email: 50972773+kyoto7250@users.noreply.github.com
Requires-Python: >=3.9,<4.0
Classifier: License :: OSI Approved :: MIT License
Classifier: Programming Language :: Python :: 3
Classifier: Programming Language :: Python :: 3.9
Classifier: Programming Language :: Python :: 3.10
Classifier: Programming Language :: Python :: 3.11
Requires-Dist: PyGithub (>=2.1.1,<3.0.0)
Requires-Dist: rich (>=13.6.0,<14.0.0)
Requires-Dist: tabulate (>=0.9.0,<0.10.0)
Project-URL: Repository, https://github.com/kyoto7250/active_pr
